{
  "project_info": {
    "project_number": "1063538673051",
    "firebase_url": "https://picfood-bd20c.firebaseio.com",
    "project_id": "picfood-bd20c",
    "storage_bucket": "picfood-bd20c.appspot.com"
  },
  "client": [
    {
      "client_info": {
        "mobilesdk_app_id": "1:1063538673051:android:f26bfc29c9beb731",
        "android_client_info": {
          "package_name": "android.picfood"
        }
      },
      "oauth_client": [
        {
          "client_id": "1063538673051-44ev3rdeu9nlikc1hthgqp1rmid1ng85.apps.googleusercontent.com",
          "client_type": 1,
          "android_info": {
            "package_name": "android.picfood",
            "certificate_hash": "73A7A41B76BDA29AC4BCD0A5D16E83ACBFDC76B1"
          }
        },
        {
          "client_id": "1063538673051-qiocui1j0hv2ivea02ii40a9lh0eaiq5.apps.googleusercontent.com",
          "client_type": 3
        }
      ],
      "api_key": [
        {
          "current_key": "AIzaSyA7TkiqkFzxsPAoxvso2pzDYssZvOLxxHQ"
        }
      ],
      "services": {
        "analytics_service": {
          "status": 1
        },
        "appinvite_service": {
          "status": 2,
          "other_platform_oauth_client": [
            {
              "client_id": "1063538673051-qiocui1j0hv2ivea02ii40a9lh0eaiq5.apps.googleusercontent.com",
              "client_type": 3
            }
          ]
        },
        "ads_service": {
          "status": 2
        }
      }
    }
  ],
  "configuration_version": "1"
}